[
  {
    "id": 241839,
    "homePlayer": {
      "id": 1433,
      "name": "HERO"
    },
    "awayPlayer": {
      "id": 1219,
      "name": "ABYSS"
    },
    "homeTeam": {
      "id": 3,
      "name": "Boston Celtics"
    },
    "awayTeam": {
      "id": 20,
      "name": "New York Knicks"
    },
    "fixtureStart": "2025-06-23T09:31:00Z",
    "raw_data": {
      "sport": "NBA",
      "avaStreamId": "sis-nba-4",
      "leagueName": null,
      "awayParticipantId": 1219,
      "tournamentName": "Ebasketball H2H GG League",
      "homeParticipantExternalId": "4401",
      "fixtureStart": "2025-06-23T09:31:00Z",
      "homeTeamId": 3,
      "groupId": null,
      "awayTeamName": "New York Knicks",
      "homeParticipantId": 1433,
      "homeTeamLogo": "teams/Boston_Celtics.svg",
      "awayTeamExternalId": null,
      "roundName": "Ebasketball H2H GG League round 1",
      "roundId": 1,
      "homeTeamName": "Boston Celtics",
      "awayParticipantLogo": "participants/ABYSS.png?v=1738339090802",
      "externalId": "NB054230625",
      "homeParticipantName": "HERO",
      "awayTeamAbbreviation": "NYK",
      "groupName": null,
      "leagueId": null,
      "fixtureExternalId": "NB054230625",
      "homeTeamExternalId": null,
      "tournamentId": 1,
      "fixtureId": 241839,
      "awayParticipantName": "ABYSS",
      "awayParticipantExternalId": "4001",
      "homeTeamAbbreviation": "BOS",
      "startDate": "2025-06-23T09:31:00Z",
      "leagueLogo": null,
      "awayTeamId": 20,
      "awayTeamLogo": "teams/NYK.png",
      "streamName": "Ebasketball 4",
      "homeParticipantLogo": "participants/HERO_1.png?v=1740571931509"
    }
  },
  {
    "id": 241886,
    "homePlayer": {
      "id": 957,
      "name": "EXO"
    },
    "awayPlayer": {
      "id": 27,
      "name": "DIMES"
    },
    "homeTeam": {
      "id": 21,
      "name": "Oklahoma City Thunder"
    },
    "awayTeam": {
      "id": 3,
      "name": "Boston Celtics"
    },
    "fixtureStart": "2025-06-23T09:39:00Z",
    "raw_data": {
      "sport": "NBA",
      "avaStreamId": "sis-nba-1",
      "leagueName": null,
      "awayParticipantId": 27,
      "tournamentName": "Ebasketball H2H GG League",
      "homeParticipantExternalId": "4286",
      "fixtureStart": "2025-06-23T09:39:00Z",
      "homeTeamId": 21,
      "groupId": null,
      "awayTeamName": "Boston Celtics",
      "homeParticipantId": 957,
      "homeTeamLogo": "teams/OKC.png",
      "awayTeamExternalId": null,
      "roundName": "Ebasketball H2H GG League round 1",
      "roundId": 1,
      "homeTeamName": "Oklahoma City Thunder",
      "awayParticipantLogo": "participants/DIMES.png",
      "externalId": "NB055230625",
      "homeParticipantName": "EXO",
      "awayTeamAbbreviation": "BOS",
      "groupName": null,
      "leagueId": null,
      "fixtureExternalId": "NB055230625",
      "homeTeamExternalId": null,
      "tournamentId": 1,
      "fixtureId": 241886,
      "awayParticipantName": "DIMES",
      "awayParticipantExternalId": "1214",
      "homeTeamAbbreviation": "OKC",
      "startDate": "2025-06-23T09:39:00Z",
      "leagueLogo": null,
      "awayTeamId": 3,
      "awayTeamLogo": "teams/Boston_Celtics.svg",
      "streamName": "Ebasketball 1",
      "homeParticipantLogo": "participants/EXO.png?v=1738341274121"
    }
  },
  {
    "id": 241925,
    "homePlayer": {
      "id": 105,
      "name": "KJMR"
    },
    "awayPlayer": {
      "id": 14,
      "name": "CARNAGE"
    },
    "homeTeam": {
      "id": 2,
      "name": "Brooklyn Nets"
    },
    "awayTeam": {
      "id": 28,
      "name": "Toronto Raptors"
    },
    "fixtureStart": "2025-06-23T09:47:00Z",
    "raw_data": {
      "sport": "NBA",
      "avaStreamId": "sis-nba-2",
      "leagueName": null,
      "awayParticipantId": 14,
      "tournamentName": "Ebasketball H2H GG League",
      "homeParticipantExternalId": "1078",
      "fixtureStart": "2025-06-23T09:47:00Z",
      "homeTeamId": 2,
      "groupId": null,
      "awayTeamName": "Toronto Raptors",
      "homeParticipantId": 105,
      "homeTeamLogo": "teams/Brooklyn_Nets.svg",
      "awayTeamExternalId": null,
      "roundName": "Ebasketball H2H GG League round 1",
      "roundId": 1,
      "homeTeamName": "Brooklyn Nets",
      "awayParticipantLogo": "participants/CARNAGE.png?v=1694789076640",
      "externalId": "NB056230625",
      "homeParticipantName": "KJMR",
      "awayTeamAbbreviation": "TOR",
      "groupName": null,
      "leagueId": null,
      "fixtureExternalId": "NB056230625",
      "homeTeamExternalId": null,
      "tournamentId": 1,
      "fixtureId": 241925,
      "awayParticipantName": "CARNAGE",
      "awayParticipantExternalId": "1239",
      "homeTeamAbbreviation": "BKN",
      "startDate": "2025-06-23T09:47:00Z",
      "leagueLogo": null,
      "awayTeamId": 28,
      "awayTeamLogo": "teams/TR.svg",
      "streamName": "Ebasketball 2",
      "homeParticipantLogo": "participants/KJMR.png"
    }
  },
  {
    "id": 241823,
    "homePlayer": {
      "id": 160,
      "name": "JUGGERNAUT"
    },
    "awayPlayer": {
      "id": 509,
      "name": "SPECTER"
    },
    "homeTeam": {
      "id": 28,
      "name": "Toronto Raptors"
    },
    "awayTeam": {
      "id": 16,
      "name": "Miami Heat"
    },
    "fixtureStart": "2025-06-23T09:55:00Z",
    "raw_data": {
      "sport": "NBA",
      "avaStreamId": "sis-nba-3",
      "leagueName": null,
      "awayParticipantId": 509,
      "tournamentName": "Ebasketball H2H GG League",
      "homeParticipantExternalId": "1269",
      "fixtureStart": "2025-06-23T09:55:00Z",
      "homeTeamId": 28,
      "groupId": null,
      "awayTeamName": "Miami Heat",
      "homeParticipantId": 160,
      "homeTeamLogo": "teams/TR.svg",
      "awayTeamExternalId": null,
      "roundName": "Ebasketball H2H GG League round 1",
      "roundId": 1,
      "homeTeamName": "Toronto Raptors",
      "awayParticipantLogo": "participants/SPECTER.png?v=1740572872596",
      "externalId": "NB057230625",
      "homeParticipantName": "JUGGERNAUT",
      "awayTeamAbbreviation": "MIA",
      "groupName": null,
      "leagueId": null,
      "fixtureExternalId": "NB057230625",
      "homeTeamExternalId": null,
      "tournamentId": 1,
      "fixtureId": 241823,
      "awayParticipantName": "SPECTER",
      "awayParticipantExternalId": "4817",
      "homeTeamAbbreviation": "TOR",
      "startDate": "2025-06-23T09:55:00Z",
      "leagueLogo": null,
      "awayTeamId": 16,
      "awayTeamLogo": "teams/MH.png",
      "streamName": "Ebasketball 3",
      "homeParticipantLogo": "participants/JUGGERNAUT.png?v=1714142097517"
    }
  },
  {
    "id": 241841,
    "homePlayer": {
      "id": 1433,
      "name": "HERO"
    },
    "awayPlayer": {
      "id": 91,
      "name": "DOUBLEFOUR"
    },
    "homeTeam": {
      "id": 8,
      "name": "Denver Nuggets"
    },
    "awayTeam": {
      "id": 4,
      "name": "Charlotte Hornets"
    },
    "fixtureStart": "2025-06-23T10:03:00Z",
    "raw_data": {
      "sport": "NBA",
      "avaStreamId": "sis-nba-4",
      "leagueName": null,
      "awayParticipantId": 91,
      "tournamentName": "Ebasketball H2H GG League",
      "homeParticipantExternalId": "4401",
      "fixtureStart": "2025-06-23T10:03:00Z",
      "homeTeamId": 8,
      "groupId": null,
      "awayTeamName": "Charlotte Hornets",
      "homeParticipantId": 1433,
      "homeTeamLogo": "teams/DN.png",
      "awayTeamExternalId": null,
      "roundName": "Ebasketball H2H GG League round 1",
      "roundId": 1,
      "homeTeamName": "Denver Nuggets",
      "awayParticipantLogo": "participants/DOUBLEFOUR.png",
      "externalId": "NB058230625",
      "homeParticipantName": "HERO",
      "awayTeamAbbreviation": "CHA",
      "groupName": null,
      "leagueId": null,
      "fixtureExternalId": "NB058230625",
      "homeTeamExternalId": null,
      "tournamentId": 1,
      "fixtureId": 241841,
      "awayParticipantName": "DOUBLEFOUR",
      "awayParticipantExternalId": "1066",
      "homeTeamAbbreviation": "DEN",
      "startDate": "2025-06-23T10:03:00Z",
      "leagueLogo": null,
      "awayTeamId": 4,
      "awayTeamLogo": "teams/CH.png",
      "streamName": "Ebasketball 4",
      "homeParticipantLogo": "participants/HERO_1.png?v=1740571931509"
    }
  },
  {
    "id": 241888,
    "homePlayer": {
      "id": 751,
      "name": "JACKAL"
    },
    "awayPlayer": {
      "id": 159,
      "name": "HOLLOW"
    },
    "homeTeam": {
      "id": 14,
      "name": "Los Angeles Lakers"
    },
    "awayTeam": {
      "id": 20,
      "name": "New York Knicks"
    },
    "fixtureStart": "2025-06-23T10:11:00Z",
    "raw_data": {
      "sport": "NBA",
      "avaStreamId": "sis-nba-1",
      "leagueName": null,
      "awayParticipantId": 159,
      "tournamentName": "Ebasketball H2H GG League",
      "homeParticipantExternalId": "4445",
      "fixtureStart": "2025-06-23T10:11:00Z",
      "homeTeamId": 14,
      "groupId": null,
      "awayTeamName": "New York Knicks",
      "homeParticipantId": 751,
      "homeTeamLogo": "teams/Los_Angeles_Lakers.svg",
      "awayTeamExternalId": null,
      "roundName": "Ebasketball H2H GG League round 1",
      "roundId": 1,
      "homeTeamName": "Los Angeles Lakers",
      "awayParticipantLogo": "participants/HOLLOW.png?v=1714140827775",
      "externalId": "NB059230625",
      "homeParticipantName": "JACKAL",
      "awayTeamAbbreviation": "NYK",
      "groupName": null,
      "leagueId": null,
      "fixtureExternalId": "NB059230625",
      "homeTeamExternalId": null,
      "tournamentId": 1,
      "fixtureId": 241888,
      "awayParticipantName": "HOLLOW",
      "awayParticipantExternalId": "1268",
      "homeTeamAbbreviation": "LAL",
      "startDate": "2025-06-23T10:11:00Z",
      "leagueLogo": null,
      "awayTeamId": 20,
      "awayTeamLogo": "teams/NYK.png",
      "streamName": "Ebasketball 1",
      "homeParticipantLogo": "participants/JACKAL.png?v=1738342862838"
    }
  },
  {
    "id": 241929,
    "homePlayer": {
      "id": 102,
      "name": "SKYFOX"
    },
    "awayPlayer": {
      "id": 66,
      "name": "THA KID"
    },
    "homeTeam": {
      "id": 16,
      "name": "Miami Heat"
    },
    "awayTeam": {
      "id": 5,
      "name": "Chicago Bulls"
    },
    "fixtureStart": "2025-06-23T10:19:00Z",
    "raw_data": {
      "sport": "NBA",
      "avaStreamId": "sis-nba-2",
      "leagueName": null,
      "awayParticipantId": 66,
      "tournamentName": "Ebasketball H2H GG League",
      "homeParticipantExternalId": "1211",
      "fixtureStart": "2025-06-23T10:19:00Z",
      "homeTeamId": 16,
      "groupId": null,
      "awayTeamName": "Chicago Bulls",
      "homeParticipantId": 102,
      "homeTeamLogo": "teams/MH.png",
      "awayTeamExternalId": null,
      "roundName": "Ebasketball H2H GG League round 1",
      "roundId": 1,
      "homeTeamName": "Miami Heat",
      "awayParticipantLogo": "participants/THA KID.png",
      "externalId": "NB060230625",
      "homeParticipantName": "SKYFOX",
      "awayTeamAbbreviation": "CHI",
      "groupName": null,
      "leagueId": null,
      "fixtureExternalId": "NB060230625",
      "homeTeamExternalId": null,
      "tournamentId": 1,
      "fixtureId": 241929,
      "awayParticipantName": "THA KID",
      "awayParticipantExternalId": "1023",
      "homeTeamAbbreviation": "MIA",
      "startDate": "2025-06-23T10:19:00Z",
      "leagueLogo": null,
      "awayTeamId": 5,
      "awayTeamLogo": "teams/CB.png",
      "streamName": "Ebasketball 2",
      "homeParticipantLogo": "participants/SKYFOX.png"
    }
  },
  {
    "id": 241813,
    "homePlayer": {
      "id": 1169,
      "name": "GODFATHER"
    },
    "awayPlayer": {
      "id": 456,
      "name": "PRIMAL"
    },
    "homeTeam": {
      "id": 24,
      "name": "Phoenix Suns"
    },
    "awayTeam": {
      "id": 15,
      "name": "Memphis Grizzlies"
    },
    "fixtureStart": "2025-06-23T10:27:00Z",
    "raw_data": {
      "sport": "NBA",
      "avaStreamId": "sis-nba-3",
      "leagueName": null,
      "awayParticipantId": 456,
      "tournamentName": "Ebasketball H2H GG League",
      "homeParticipantExternalId": "4348",
      "fixtureStart": "2025-06-23T10:27:00Z",
      "homeTeamId": 24,
      "groupId": null,
      "awayTeamName": "Memphis Grizzlies",
      "homeParticipantId": 1169,
      "homeTeamLogo": "teams/Phoenix_Suns.svg",
      "awayTeamExternalId": null,
      "roundName": "Ebasketball H2H GG League round 1",
      "roundId": 1,
      "homeTeamName": "Phoenix Suns",
      "awayParticipantLogo": "participants/PRIMAL.png?v=1722868829330",
      "externalId": "NB061230625",
      "homeParticipantName": "GODFATHER",
      "awayTeamAbbreviation": "MEM",
      "groupName": null,
      "leagueId": null,
      "fixtureExternalId": "NB061230625",
      "homeTeamExternalId": null,
      "tournamentId": 1,
      "fixtureId": 241813,
      "awayParticipantName": "PRIMAL",
      "awayParticipantExternalId": "4643",
      "homeTeamAbbreviation": "PHX",
      "startDate": "2025-06-23T10:27:00Z",
      "leagueLogo": null,
      "awayTeamId": 15,
      "awayTeamLogo": "teams/Memphis_Grizzlies.svg",
      "streamName": "Ebasketball 3",
      "homeParticipantLogo": "participants/GODFATHER.png?v=1738342374988"
    }
  },
  {
    "id": 241852,
    "homePlayer": {
      "id": 1219,
      "name": "ABYSS"
    },
    "awayPlayer": {
      "id": 2249,
      "name": "DOC"
    },
    "homeTeam": {
      "id": 20,
      "name": "New York Knicks"
    },
    "awayTeam": {
      "id": 21,
      "name": "Oklahoma City Thunder"
    },
    "fixtureStart": "2025-06-23T10:35:00Z",
    "raw_data": {
      "sport": "NBA",
      "avaStreamId": "sis-nba-4",
      "leagueName": null,
      "awayParticipantId": 2249,
      "tournamentName": "Ebasketball H2H GG League",
      "homeParticipantExternalId": "4001",
      "fixtureStart": "2025-06-23T10:35:00Z",
      "homeTeamId": 20,
      "groupId": null,
      "awayTeamName": "Oklahoma City Thunder",
      "homeParticipantId": 1219,
      "homeTeamLogo": "teams/NYK.png",
      "awayTeamExternalId": null,
      "roundName": "Ebasketball H2H GG League round 1",
      "roundId": 1,
      "homeTeamName": "New York Knicks",
      "awayParticipantLogo": "participants/default-player-profile.png",
      "externalId": "NB062230625",
      "homeParticipantName": "ABYSS",
      "awayTeamAbbreviation": "OKC",
      "groupName": null,
      "leagueId": null,
      "fixtureExternalId": "NB062230625",
      "homeTeamExternalId": null,
      "tournamentId": 1,
      "fixtureId": 241852,
      "awayParticipantName": "DOC",
      "awayParticipantExternalId": "4235",
      "homeTeamAbbreviation": "NYK",
      "startDate": "2025-06-23T10:35:00Z",
      "leagueLogo": null,
      "awayTeamId": 21,
      "awayTeamLogo": "teams/OKC.png",
      "streamName": "Ebasketball 4",
      "homeParticipantLogo": "participants/ABYSS.png?v=1738339090802"
    }
  },
  {
    "id": 241873,
    "homePlayer": {
      "id": 957,
      "name": "EXO"
    },
    "awayPlayer": {
      "id": 159,
      "name": "HOLLOW"
    },
    "homeTeam": {
      "id": 21,
      "name": "Oklahoma City Thunder"
    },
    "awayTeam": {
      "id": 20,
      "name": "New York Knicks"
    },
    "fixtureStart": "2025-06-23T10:43:00Z",
    "raw_data": {
      "sport": "NBA",
      "avaStreamId": "sis-nba-1",
      "leagueName": null,
      "awayParticipantId": 159,
      "tournamentName": "Ebasketball H2H GG League",
      "homeParticipantExternalId": "4286",
      "fixtureStart": "2025-06-23T10:43:00Z",
      "homeTeamId": 21,
      "groupId": null,
      "awayTeamName": "New York Knicks",
      "homeParticipantId": 957,
      "homeTeamLogo": "teams/OKC.png",
      "awayTeamExternalId": null,
      "roundName": "Ebasketball H2H GG League round 1",
      "roundId": 1,
      "homeTeamName": "Oklahoma City Thunder",
      "awayParticipantLogo": "participants/HOLLOW.png?v=1714140827775",
      "externalId": "NB063230625",
      "homeParticipantName": "EXO",
      "awayTeamAbbreviation": "NYK",
      "groupName": null,
      "leagueId": null,
      "fixtureExternalId": "NB063230625",
      "homeTeamExternalId": null,
      "tournamentId": 1,
      "fixtureId": 241873,
      "awayParticipantName": "HOLLOW",
      "awayParticipantExternalId": "1268",
      "homeTeamAbbreviation": "OKC",
      "startDate": "2025-06-23T10:43:00Z",
      "leagueLogo": null,
      "awayTeamId": 20,
      "awayTeamLogo": "teams/NYK.png",
      "streamName": "Ebasketball 1",
      "homeParticipantLogo": "participants/EXO.png?v=1738341274121"
    }
  },
  {
    "id": 241926,
    "homePlayer": {
      "id": 105,
      "name": "KJMR"
    },
    "awayPlayer": {
      "id": 66,
      "name": "THA KID"
    },
    "homeTeam": {
      "id": 2,
      "name": "Brooklyn Nets"
    },
    "awayTeam": {
      "id": 5,
      "name": "Chicago Bulls"
    },
    "fixtureStart": "2025-06-23T10:51:00Z",
    "raw_data": {
      "sport": "NBA",
      "avaStreamId": "sis-nba-2",
      "leagueName": null,
      "awayParticipantId": 66,
      "tournamentName": "Ebasketball H2H GG League",
      "homeParticipantExternalId": "1078",
      "fixtureStart": "2025-06-23T10:51:00Z",
      "homeTeamId": 2,
      "groupId": null,
      "awayTeamName": "Chicago Bulls",
      "homeParticipantId": 105,
      "homeTeamLogo": "teams/Brooklyn_Nets.svg",
      "awayTeamExternalId": null,
      "roundName": "Ebasketball H2H GG League round 1",
      "roundId": 1,
      "homeTeamName": "Brooklyn Nets",
      "awayParticipantLogo": "participants/THA KID.png",
      "externalId": "NB064230625",
      "homeParticipantName": "KJMR",
      "awayTeamAbbreviation": "CHI",
      "groupName": null,
      "leagueId": null,
      "fixtureExternalId": "NB064230625",
      "homeTeamExternalId": null,
      "tournamentId": 1,
      "fixtureId": 241926,
      "awayParticipantName": "THA KID",
      "awayParticipantExternalId": "1023",
      "homeTeamAbbreviation": "BKN",
      "startDate": "2025-06-23T10:51:00Z",
      "leagueLogo": null,
      "awayTeamId": 5,
      "awayTeamLogo": "teams/CB.png",
      "streamName": "Ebasketball 2",
      "homeParticipantLogo": "participants/KJMR.png"
    }
  },
  {
    "id": 241817,
    "homePlayer": {
      "id": 160,
      "name": "JUGGERNAUT"
    },
    "awayPlayer": {
      "id": 456,
      "name": "PRIMAL"
    },
    "homeTeam": {
      "id": 28,
      "name": "Toronto Raptors"
    },
    "awayTeam": {
      "id": 2,
      "name": "Brooklyn Nets"
    },
    "fixtureStart": "2025-06-23T10:59:00Z",
    "raw_data": {
      "sport": "NBA",
      "avaStreamId": "sis-nba-3",
      "leagueName": null,
      "awayParticipantId": 456,
      "tournamentName": "Ebasketball H2H GG League",
      "homeParticipantExternalId": "1269",
      "fixtureStart": "2025-06-23T10:59:00Z",
      "homeTeamId": 28,
      "groupId": null,
      "awayTeamName": "Brooklyn Nets",
      "homeParticipantId": 160,
      "homeTeamLogo": "teams/TR.svg",
      "awayTeamExternalId": null,
      "roundName": "Ebasketball H2H GG League round 1",
      "roundId": 1,
      "homeTeamName": "Toronto Raptors",
      "awayParticipantLogo": "participants/PRIMAL.png?v=1722868829330",
      "externalId": "NB065230625",
      "homeParticipantName": "JUGGERNAUT",
      "awayTeamAbbreviation": "BKN",
      "groupName": null,
      "leagueId": null,
      "fixtureExternalId": "NB065230625",
      "homeTeamExternalId": null,
      "tournamentId": 1,
      "fixtureId": 241817,
      "awayParticipantName": "PRIMAL",
      "awayParticipantExternalId": "4643",
      "homeTeamAbbreviation": "TOR",
      "startDate": "2025-06-23T10:59:00Z",
      "leagueLogo": null,
      "awayTeamId": 2,
      "awayTeamLogo": "teams/Brooklyn_Nets.svg",
      "streamName": "Ebasketball 3",
      "homeParticipantLogo": "participants/JUGGERNAUT.png?v=1714142097517"
    }
  },
  {
    "id": 241859,
    "homePlayer": {
      "id": 1433,
      "name": "HERO"
    },
    "awayPlayer": {
      "id": 2249,
      "name": "DOC"
    },
    "homeTeam": {
      "id": 8,
      "name": "Denver Nuggets"
    },
    "awayTeam": {
      "id": 7,
      "name": "Dallas Mavericks"
    },
    "fixtureStart": "2025-06-23T11:07:00Z",
    "raw_data": {
      "sport": "NBA",
      "avaStreamId": "sis-nba-4",
      "leagueName": null,
      "awayParticipantId": 2249,
      "tournamentName": "Ebasketball H2H GG League",
      "homeParticipantExternalId": "4401",
      "fixtureStart": "2025-06-23T11:07:00Z",
      "homeTeamId": 8,
      "groupId": null,
      "awayTeamName": "Dallas Mavericks",
      "homeParticipantId": 1433,
      "homeTeamLogo": "teams/DN.png",
      "awayTeamExternalId": null,
      "roundName": "Ebasketball H2H GG League round 1",
      "roundId": 1,
      "homeTeamName": "Denver Nuggets",
      "awayParticipantLogo": "participants/default-player-profile.png",
      "externalId": "NB066230625",
      "homeParticipantName": "HERO",
      "awayTeamAbbreviation": "DAL",
      "groupName": null,
      "leagueId": null,
      "fixtureExternalId": "NB066230625",
      "homeTeamExternalId": null,
      "tournamentId": 1,
      "fixtureId": 241859,
      "awayParticipantName": "DOC",
      "awayParticipantExternalId": "4235",
      "homeTeamAbbreviation": "DEN",
      "startDate": "2025-06-23T11:07:00Z",
      "leagueLogo": null,
      "awayTeamId": 7,
      "awayTeamLogo": "teams/Dallas_Mavericks.svg",
      "streamName": "Ebasketball 4",
      "homeParticipantLogo": "participants/HERO_1.png?v=1740571931509"
    }
  },
  {
    "id": 241893,
    "homePlayer": {
      "id": 751,
      "name": "JACKAL"
    },
    "awayPlayer": {
      "id": 27,
      "name": "DIMES"
    },
    "homeTeam": {
      "id": 14,
      "name": "Los Angeles Lakers"
    },
    "awayTeam": {
      "id": 3,
      "name": "Boston Celtics"
    },
    "fixtureStart": "2025-06-23T11:15:00Z",
    "raw_data": {
      "sport": "NBA",
      "avaStreamId": "sis-nba-1",
      "leagueName": null,
      "awayParticipantId": 27,
      "tournamentName": "Ebasketball H2H GG League",
      "homeParticipantExternalId": "4445",
      "fixtureStart": "2025-06-23T11:15:00Z",
      "homeTeamId": 14,
      "groupId": null,
      "awayTeamName": "Boston Celtics",
      "homeParticipantId": 751,
      "homeTeamLogo": "teams/Los_Angeles_Lakers.svg",
      "awayTeamExternalId": null,
      "roundName": "Ebasketball H2H GG League round 1",
      "roundId": 1,
      "homeTeamName": "Los Angeles Lakers",
      "awayParticipantLogo": "participants/DIMES.png",
      "externalId": "NB067230625",
      "homeParticipantName": "JACKAL",
      "awayTeamAbbreviation": "BOS",
      "groupName": null,
      "leagueId": null,
      "fixtureExternalId": "NB067230625",
      "homeTeamExternalId": null,
      "tournamentId": 1,
      "fixtureId": 241893,
      "awayParticipantName": "DIMES",
      "awayParticipantExternalId": "1214",
      "homeTeamAbbreviation": "LAL",
      "startDate": "2025-06-23T11:15:00Z",
      "leagueLogo": null,
      "awayTeamId": 3,
      "awayTeamLogo": "teams/Boston_Celtics.svg",
      "streamName": "Ebasketball 1",
      "homeParticipantLogo": "participants/JACKAL.png?v=1738342862838"
    }
  },
  {
    "id": 241924,
    "homePlayer": {
      "id": 102,
      "name": "SKYFOX"
    },
    "awayPlayer": {
      "id": 14,
      "name": "CARNAGE"
    },
    "homeTeam": {
      "id": 16,
      "name": "Miami Heat"
    },
    "awayTeam": {
      "id": 28,
      "name": "Toronto Raptors"
    },
    "fixtureStart": "2025-06-23T11:23:00Z",
    "raw_data": {
      "sport": "NBA",
      "avaStreamId": "sis-nba-2",
      "leagueName": null,
      "awayParticipantId": 14,
      "tournamentName": "Ebasketball H2H GG League",
      "homeParticipantExternalId": "1211",
      "fixtureStart": "2025-06-23T11:23:00Z",
      "homeTeamId": 16,
      "groupId": null,
      "awayTeamName": "Toronto Raptors",
      "homeParticipantId": 102,
      "homeTeamLogo": "teams/MH.png",
      "awayTeamExternalId": null,
      "roundName": "Ebasketball H2H GG League round 1",
      "roundId": 1,
      "homeTeamName": "Miami Heat",
      "awayParticipantLogo": "participants/CARNAGE.png?v=1694789076640",
      "externalId": "NB068230625",
      "homeParticipantName": "SKYFOX",
      "awayTeamAbbreviation": "TOR",
      "groupName": null,
      "leagueId": null,
      "fixtureExternalId": "NB068230625",
      "homeTeamExternalId": null,
      "tournamentId": 1,
      "fixtureId": 241924,
      "awayParticipantName": "CARNAGE",
      "awayParticipantExternalId": "1239",
      "homeTeamAbbreviation": "MIA",
      "startDate": "2025-06-23T11:23:00Z",
      "leagueLogo": null,
      "awayTeamId": 28,
      "awayTeamLogo": "teams/TR.svg",
      "streamName": "Ebasketball 2",
      "homeParticipantLogo": "participants/SKYFOX.png"
    }
  },
  {
    "id": 241810,
    "homePlayer": {
      "id": 1169,
      "name": "GODFATHER"
    },
    "awayPlayer": {
      "id": 509,
      "name": "SPECTER"
    },
    "homeTeam": {
      "id": 24,
      "name": "Phoenix Suns"
    },
    "awayTeam": {
      "id": 17,
      "name": "Milwaukee Bucks"
    },
    "fixtureStart": "2025-06-23T11:31:00Z",
    "raw_data": {
      "sport": "NBA",
      "avaStreamId": "sis-nba-3",
      "leagueName": null,
      "awayParticipantId": 509,
      "tournamentName": "Ebasketball H2H GG League",
      "homeParticipantExternalId": "4348",
      "fixtureStart": "2025-06-23T11:31:00Z",
      "homeTeamId": 24,
      "groupId": null,
      "awayTeamName": "Milwaukee Bucks",
      "homeParticipantId": 1169,
      "homeTeamLogo": "teams/Phoenix_Suns.svg",
      "awayTeamExternalId": null,
      "roundName": "Ebasketball H2H GG League round 1",
      "roundId": 1,
      "homeTeamName": "Phoenix Suns",
      "awayParticipantLogo": "participants/SPECTER.png?v=1740572872596",
      "externalId": "NB069230625",
      "homeParticipantName": "GODFATHER",
      "awayTeamAbbreviation": "MIL",
      "groupName": null,
      "leagueId": null,
      "fixtureExternalId": "NB069230625",
      "homeTeamExternalId": null,
      "tournamentId": 1,
      "fixtureId": 241810,
      "awayParticipantName": "SPECTER",
      "awayParticipantExternalId": "4817",
      "homeTeamAbbreviation": "PHX",
      "startDate": "2025-06-23T11:31:00Z",
      "leagueLogo": null,
      "awayTeamId": 17,
      "awayTeamLogo": "teams/Milwaukee_Bucks.svg",
      "streamName": "Ebasketball 3",
      "homeParticipantLogo": "participants/GODFATHER.png?v=1738342374988"
    }
  },
  {
    "id": 241858,
    "homePlayer": {
      "id": 1219,
      "name": "ABYSS"
    },
    "awayPlayer": {
      "id": 91,
      "name": "DOUBLEFOUR"
    },
    "homeTeam": {
      "id": 20,
      "name": "New York Knicks"
    },
    "awayTeam": {
      "id": 14,
      "name": "Los Angeles Lakers"
    },
    "fixtureStart": "2025-06-23T11:39:00Z",
    "raw_data": {
      "sport": "NBA",
      "avaStreamId": "sis-nba-4",
      "leagueName": null,
      "awayParticipantId": 91,
      "tournamentName": "Ebasketball H2H GG League",
      "homeParticipantExternalId": "4001",
      "fixtureStart": "2025-06-23T11:39:00Z",
      "homeTeamId": 20,
      "groupId": null,
      "awayTeamName": "Los Angeles Lakers",
      "homeParticipantId": 1219,
      "homeTeamLogo": "teams/NYK.png",
      "awayTeamExternalId": null,
      "roundName": "Ebasketball H2H GG League round 1",
      "roundId": 1,
      "homeTeamName": "New York Knicks",
      "awayParticipantLogo": "participants/DOUBLEFOUR.png",
      "externalId": "NB070230625",
      "homeParticipantName": "ABYSS",
      "awayTeamAbbreviation": "LAL",
      "groupName": null,
      "leagueId": null,
      "fixtureExternalId": "NB070230625",
      "homeTeamExternalId": null,
      "tournamentId": 1,
      "fixtureId": 241858,
      "awayParticipantName": "DOUBLEFOUR",
      "awayParticipantExternalId": "1066",
      "homeTeamAbbreviation": "NYK",
      "startDate": "2025-06-23T11:39:00Z",
      "leagueLogo": null,
      "awayTeamId": 14,
      "awayTeamLogo": "teams/Los_Angeles_Lakers.svg",
      "streamName": "Ebasketball 4",
      "homeParticipantLogo": "participants/ABYSS.png?v=1738339090802"
    }
  },
  {
    "id": 241875,
    "homePlayer": {
      "id": 27,
      "name": "DIMES"
    },
    "awayPlayer": {
      "id": 159,
      "name": "HOLLOW"
    },
    "homeTeam": {
      "id": 7,
      "name": "Dallas Mavericks"
    },
    "awayTeam": {
      "id": 8,
      "name": "Denver Nuggets"
    },
    "fixtureStart": "2025-06-23T11:47:00Z",
    "raw_data": {
      "sport": "NBA",
      "avaStreamId": "sis-nba-1",
      "leagueName": null,
      "awayParticipantId": 159,
      "tournamentName": "Ebasketball H2H GG League",
      "homeParticipantExternalId": "1214",
      "fixtureStart": "2025-06-23T11:47:00Z",
      "homeTeamId": 7,
      "groupId": null,
      "awayTeamName": "Denver Nuggets",
      "homeParticipantId": 27,
      "homeTeamLogo": "teams/Dallas_Mavericks.svg",
      "awayTeamExternalId": null,
      "roundName": "Ebasketball H2H GG League round 1",
      "roundId": 1,
      "homeTeamName": "Dallas Mavericks",
      "awayParticipantLogo": "participants/HOLLOW.png?v=1714140827775",
      "externalId": "NB071230625",
      "homeParticipantName": "DIMES",
      "awayTeamAbbreviation": "DEN",
      "groupName": null,
      "leagueId": null,
      "fixtureExternalId": "NB071230625",
      "homeTeamExternalId": null,
      "tournamentId": 1,
      "fixtureId": 241875,
      "awayParticipantName": "HOLLOW",
      "awayParticipantExternalId": "1268",
      "homeTeamAbbreviation": "DAL",
      "startDate": "2025-06-23T11:47:00Z",
      "leagueLogo": null,
      "awayTeamId": 8,
      "awayTeamLogo": "teams/DN.png",
      "streamName": "Ebasketball 1",
      "homeParticipantLogo": "participants/DIMES.png"
    }
  },
  {
    "id": 241903,
    "homePlayer": {
      "id": 14,
      "name": "CARNAGE"
    },
    "awayPlayer": {
      "id": 66,
      "name": "THA KID"
    },
    "homeTeam": {
      "id": 24,
      "name": "Phoenix Suns"
    },
    "awayTeam": {
      "id": 15,
      "name": "Memphis Grizzlies"
    },
    "fixtureStart": "2025-06-23T11:55:00Z",
    "raw_data": {
      "sport": "NBA",
      "avaStreamId": "sis-nba-2",
      "leagueName": null,
      "awayParticipantId": 66,
      "tournamentName": "Ebasketball H2H GG League",
      "homeParticipantExternalId": "1239",
      "fixtureStart": "2025-06-23T11:55:00Z",
      "homeTeamId": 24,
      "groupId": null,
      "awayTeamName": "Memphis Grizzlies",
      "homeParticipantId": 14,
      "homeTeamLogo": "teams/Phoenix_Suns.svg",
      "awayTeamExternalId": null,
      "roundName": "Ebasketball H2H GG League round 1",
      "roundId": 1,
      "homeTeamName": "Phoenix Suns",
      "awayParticipantLogo": "participants/THA KID.png",
      "externalId": "NB072230625",
      "homeParticipantName": "CARNAGE",
      "awayTeamAbbreviation": "MEM",
      "groupName": null,
      "leagueId": null,
      "fixtureExternalId": "NB072230625",
      "homeTeamExternalId": null,
      "tournamentId": 1,
      "fixtureId": 241903,
      "awayParticipantName": "THA KID",
      "awayParticipantExternalId": "1023",
      "homeTeamAbbreviation": "PHX",
      "startDate": "2025-06-23T11:55:00Z",
      "leagueLogo": null,
      "awayTeamId": 15,
      "awayTeamLogo": "teams/Memphis_Grizzlies.svg",
      "streamName": "Ebasketball 2",
      "homeParticipantLogo": "participants/CARNAGE.png?v=1694789076640"
    }
  },
  {
    "id": 241836,
    "homePlayer": {
      "id": 509,
      "name": "SPECTER"
    },
    "awayPlayer": {
      "id": 456,
      "name": "PRIMAL"
    },
    "homeTeam": {
      "id": 16,
      "name": "Miami Heat"
    },
    "awayTeam": {
      "id": 2,
      "name": "Brooklyn Nets"
    },
    "fixtureStart": "2025-06-23T12:03:00Z",
    "raw_data": {
      "sport": "NBA",
      "avaStreamId": "sis-nba-3",
      "leagueName": null,
      "awayParticipantId": 456,
      "tournamentName": "Ebasketball H2H GG League",
      "homeParticipantExternalId": "4817",
      "fixtureStart": "2025-06-23T12:03:00Z",
      "homeTeamId": 16,
      "groupId": null,
      "awayTeamName": "Brooklyn Nets",
      "homeParticipantId": 509,
      "homeTeamLogo": "teams/MH.png",
      "awayTeamExternalId": null,
      "roundName": "Ebasketball H2H GG League round 1",
      "roundId": 1,
      "homeTeamName": "Miami Heat",
      "awayParticipantLogo": "participants/PRIMAL.png?v=1722868829330",
      "externalId": "NB073230625",
      "homeParticipantName": "SPECTER",
      "awayTeamAbbreviation": "BKN",
      "groupName": null,
      "leagueId": null,
      "fixtureExternalId": "NB073230625",
      "homeTeamExternalId": null,
      "tournamentId": 1,
      "fixtureId": 241836,
      "awayParticipantName": "PRIMAL",
      "awayParticipantExternalId": "4643",
      "homeTeamAbbreviation": "MIA",
      "startDate": "2025-06-23T12:03:00Z",
      "leagueLogo": null,
      "awayTeamId": 2,
      "awayTeamLogo": "teams/Brooklyn_Nets.svg",
      "streamName": "Ebasketball 3",
      "homeParticipantLogo": "participants/SPECTER.png?v=1740572872596"
    }
  },
  {
    "id": 241843,
    "homePlayer": {
      "id": 91,
      "name": "DOUBLEFOUR"
    },
    "awayPlayer": {
      "id": 2249,
      "name": "DOC"
    },
    "homeTeam": {
      "id": 4,
      "name": "Charlotte Hornets"
    },
    "awayTeam": {
      "id": 7,
      "name": "Dallas Mavericks"
    },
    "fixtureStart": "2025-06-23T12:11:00Z",
    "raw_data": {
      "sport": "NBA",
      "avaStreamId": "sis-nba-4",
      "leagueName": null,
      "awayParticipantId": 2249,
      "tournamentName": "Ebasketball H2H GG League",
      "homeParticipantExternalId": "1066",
      "fixtureStart": "2025-06-23T12:11:00Z",
      "homeTeamId": 4,
      "groupId": null,
      "awayTeamName": "Dallas Mavericks",
      "homeParticipantId": 91,
      "homeTeamLogo": "teams/CH.png",
      "awayTeamExternalId": null,
      "roundName": "Ebasketball H2H GG League round 1",
      "roundId": 1,
      "homeTeamName": "Charlotte Hornets",
      "awayParticipantLogo": "participants/default-player-profile.png",
      "externalId": "NB074230625",
      "homeParticipantName": "DOUBLEFOUR",
      "awayTeamAbbreviation": "DAL",
      "groupName": null,
      "leagueId": null,
      "fixtureExternalId": "NB074230625",
      "homeTeamExternalId": null,
      "tournamentId": 1,
      "fixtureId": 241843,
      "awayParticipantName": "DOC",
      "awayParticipantExternalId": "4235",
      "homeTeamAbbreviation": "CHA",
      "startDate": "2025-06-23T12:11:00Z",
      "leagueLogo": null,
      "awayTeamId": 7,
      "awayTeamLogo": "teams/Dallas_Mavericks.svg",
      "streamName": "Ebasketball 4",
      "homeParticipantLogo": "participants/DOUBLEFOUR.png"
    }
  },
  {
    "id": 241884,
    "homePlayer": {
      "id": 751,
      "name": "JACKAL"
    },
    "awayPlayer": {
      "id": 957,
      "name": "EXO"
    },
    "homeTeam": {
      "id": 4,
      "name": "Charlotte Hornets"
    },
    "awayTeam": {
      "id": 22,
      "name": "Orlando Magic"
    },
    "fixtureStart": "2025-06-23T12:19:00Z",
    "raw_data": {
      "sport": "NBA",
      "avaStreamId": "sis-nba-1",
      "leagueName": null,
      "awayParticipantId": 957,
      "tournamentName": "Ebasketball H2H GG League",
      "homeParticipantExternalId": "4445",
      "fixtureStart": "2025-06-23T12:19:00Z",
      "homeTeamId": 4,
      "groupId": null,
      "awayTeamName": "Orlando Magic",
      "homeParticipantId": 751,
      "homeTeamLogo": "teams/CH.png",
      "awayTeamExternalId": null,
      "roundName": "Ebasketball H2H GG League round 1",
      "roundId": 1,
      "homeTeamName": "Charlotte Hornets",
      "awayParticipantLogo": "participants/EXO.png?v=1738341274121",
      "externalId": "NB075230625",
      "homeParticipantName": "JACKAL",
      "awayTeamAbbreviation": "ORL",
      "groupName": null,
      "leagueId": null,
      "fixtureExternalId": "NB075230625",
      "homeTeamExternalId": null,
      "tournamentId": 1,
      "fixtureId": 241884,
      "awayParticipantName": "EXO",
      "awayParticipantExternalId": "4286",
      "homeTeamAbbreviation": "CHA",
      "startDate": "2025-06-23T12:19:00Z",
      "leagueLogo": null,
      "awayTeamId": 22,
      "awayTeamLogo": "teams/OM.png",
      "streamName": "Ebasketball 1",
      "homeParticipantLogo": "participants/JACKAL.png?v=1738342862838"
    }
  },
  {
    "id": 241918,
    "homePlayer": {
      "id": 102,
      "name": "SKYFOX"
    },
    "awayPlayer": {
      "id": 105,
      "name": "KJMR"
    },
    "homeTeam": {
      "id": 6,
      "name": "Cleveland Cavaliers"
    },
    "awayTeam": {
      "id": 17,
      "name": "Milwaukee Bucks"
    },
    "fixtureStart": "2025-06-23T12:27:00Z",
    "raw_data": {
      "sport": "NBA",
      "avaStreamId": "sis-nba-2",
      "leagueName": null,
      "awayParticipantId": 105,
      "tournamentName": "Ebasketball H2H GG League",
      "homeParticipantExternalId": "1211",
      "fixtureStart": "2025-06-23T12:27:00Z",
      "homeTeamId": 6,
      "groupId": null,
      "awayTeamName": "Milwaukee Bucks",
      "homeParticipantId": 102,
      "homeTeamLogo": "teams/Cleveland_Cavaliers.svg",
      "awayTeamExternalId": null,
      "roundName": "Ebasketball H2H GG League round 1",
      "roundId": 1,
      "homeTeamName": "Cleveland Cavaliers",
      "awayParticipantLogo": "participants/KJMR.png",
      "externalId": "NB076230625",
      "homeParticipantName": "SKYFOX",
      "awayTeamAbbreviation": "MIL",
      "groupName": null,
      "leagueId": null,
      "fixtureExternalId": "NB076230625",
      "homeTeamExternalId": null,
      "tournamentId": 1,
      "fixtureId": 241918,
      "awayParticipantName": "KJMR",
      "awayParticipantExternalId": "1078",
      "homeTeamAbbreviation": "CLE",
      "startDate": "2025-06-23T12:27:00Z",
      "leagueLogo": null,
      "awayTeamId": 17,
      "awayTeamLogo": "teams/Milwaukee_Bucks.svg",
      "streamName": "Ebasketball 2",
      "homeParticipantLogo": "participants/SKYFOX.png"
    }
  },
  {
    "id": 241830,
    "homePlayer": {
      "id": 1169,
      "name": "GODFATHER"
    },
    "awayPlayer": {
      "id": 160,
      "name": "JUGGERNAUT"
    },
    "homeTeam": {
      "id": 24,
      "name": "Phoenix Suns"
    },
    "awayTeam": {
      "id": 6,
      "name": "Cleveland Cavaliers"
    },
    "fixtureStart": "2025-06-23T12:35:00Z",
    "raw_data": {
      "sport": "NBA",
      "avaStreamId": "sis-nba-3",
      "leagueName": null,
      "awayParticipantId": 160,
      "tournamentName": "Ebasketball H2H GG League",
      "homeParticipantExternalId": "4348",
      "fixtureStart": "2025-06-23T12:35:00Z",
      "homeTeamId": 24,
      "groupId": null,
      "awayTeamName": "Cleveland Cavaliers",
      "homeParticipantId": 1169,
      "homeTeamLogo": "teams/Phoenix_Suns.svg",
      "awayTeamExternalId": null,
      "roundName": "Ebasketball H2H GG League round 1",
      "roundId": 1,
      "homeTeamName": "Phoenix Suns",
      "awayParticipantLogo": "participants/JUGGERNAUT.png?v=1714142097517",
      "externalId": "NB077230625",
      "homeParticipantName": "GODFATHER",
      "awayTeamAbbreviation": "CLE",
      "groupName": null,
      "leagueId": null,
      "fixtureExternalId": "NB077230625",
      "homeTeamExternalId": null,
      "tournamentId": 1,
      "fixtureId": 241830,
      "awayParticipantName": "JUGGERNAUT",
      "awayParticipantExternalId": "1269",
      "homeTeamAbbreviation": "PHX",
      "startDate": "2025-06-23T12:35:00Z",
      "leagueLogo": null,
      "awayTeamId": 6,
      "awayTeamLogo": "teams/Cleveland_Cavaliers.svg",
      "streamName": "Ebasketball 3",
      "homeParticipantLogo": "participants/GODFATHER.png?v=1738342374988"
    }
  },
  {
    "id": 241847,
    "homePlayer": {
      "id": 1219,
      "name": "ABYSS"
    },
    "awayPlayer": {
      "id": 1433,
      "name": "HERO"
    },
    "homeTeam": {
      "id": 20,
      "name": "New York Knicks"
    },
    "awayTeam": {
      "id": 3,
      "name": "Boston Celtics"
    },
    "fixtureStart": "2025-06-23T12:43:00Z",
    "raw_data": {
      "sport": "NBA",
      "avaStreamId": "sis-nba-4",
      "leagueName": null,
      "awayParticipantId": 1433,
      "tournamentName": "Ebasketball H2H GG League",
      "homeParticipantExternalId": "4001",
      "fixtureStart": "2025-06-23T12:43:00Z",
      "homeTeamId": 20,
      "groupId": null,
      "awayTeamName": "Boston Celtics",
      "homeParticipantId": 1219,
      "homeTeamLogo": "teams/NYK.png",
      "awayTeamExternalId": null,
      "roundName": "Ebasketball H2H GG League round 1",
      "roundId": 1,
      "homeTeamName": "New York Knicks",
      "awayParticipantLogo": "participants/HERO_1.png?v=1740571931509",
      "externalId": "NB078230625",
      "homeParticipantName": "ABYSS",
      "awayTeamAbbreviation": "BOS",
      "groupName": null,
      "leagueId": null,
      "fixtureExternalId": "NB078230625",
      "homeTeamExternalId": null,
      "tournamentId": 1,
      "fixtureId": 241847,
      "awayParticipantName": "HERO",
      "awayParticipantExternalId": "4401",
      "homeTeamAbbreviation": "NYK",
      "startDate": "2025-06-23T12:43:00Z",
      "leagueLogo": null,
      "awayTeamId": 3,
      "awayTeamLogo": "teams/Boston_Celtics.svg",
      "streamName": "Ebasketball 4",
      "homeParticipantLogo": "participants/ABYSS.png?v=1738339090802"
    }
  },
  {
    "id": 241887,
    "homePlayer": {
      "id": 159,
      "name": "HOLLOW"
    },
    "awayPlayer": {
      "id": 27,
      "name": "DIMES"
    },
    "homeTeam": {
      "id": 8,
      "name": "Denver Nuggets"
    },
    "awayTeam": {
      "id": 7,
      "name": "Dallas Mavericks"
    },
    "fixtureStart": "2025-06-23T12:51:00Z",
    "raw_data": {
      "sport": "NBA",
      "avaStreamId": "sis-nba-1",
      "leagueName": null,
      "awayParticipantId": 27,
      "tournamentName": "Ebasketball H2H GG League",
      "homeParticipantExternalId": "1268",
      "fixtureStart": "2025-06-23T12:51:00Z",
      "homeTeamId": 8,
      "groupId": null,
      "awayTeamName": "Dallas Mavericks",
      "homeParticipantId": 159,
      "homeTeamLogo": "teams/DN.png",
      "awayTeamExternalId": null,
      "roundName": "Ebasketball H2H GG League round 1",
      "roundId": 1,
      "homeTeamName": "Denver Nuggets",
      "awayParticipantLogo": "participants/DIMES.png",
      "externalId": "NB079230625",
      "homeParticipantName": "HOLLOW",
      "awayTeamAbbreviation": "DAL",
      "groupName": null,
      "leagueId": null,
      "fixtureExternalId": "NB079230625",
      "homeTeamExternalId": null,
      "tournamentId": 1,
      "fixtureId": 241887,
      "awayParticipantName": "DIMES",
      "awayParticipantExternalId": "1214",
      "homeTeamAbbreviation": "DEN",
      "startDate": "2025-06-23T12:51:00Z",
      "leagueLogo": null,
      "awayTeamId": 7,
      "awayTeamLogo": "teams/Dallas_Mavericks.svg",
      "streamName": "Ebasketball 1",
      "homeParticipantLogo": "participants/HOLLOW.png?v=1714140827775"
    }
  },
  {
    "id": 241907,
    "homePlayer": {
      "id": 66,
      "name": "THA KID"
    },
    "awayPlayer": {
      "id": 14,
      "name": "CARNAGE"
    },
    "homeTeam": {
      "id": 15,
      "name": "Memphis Grizzlies"
    },
    "awayTeam": {
      "id": 24,
      "name": "Phoenix Suns"
    },
    "fixtureStart": "2025-06-23T12:59:00Z",
    "raw_data": {
      "sport": "NBA",
      "avaStreamId": "sis-nba-2",
      "leagueName": null,
      "awayParticipantId": 14,
      "tournamentName": "Ebasketball H2H GG League",
      "homeParticipantExternalId": "1023",
      "fixtureStart": "2025-06-23T12:59:00Z",
      "homeTeamId": 15,
      "groupId": null,
      "awayTeamName": "Phoenix Suns",
      "homeParticipantId": 66,
      "homeTeamLogo": "teams/Memphis_Grizzlies.svg",
      "awayTeamExternalId": null,
      "roundName": "Ebasketball H2H GG League round 1",
      "roundId": 1,
      "homeTeamName": "Memphis Grizzlies",
      "awayParticipantLogo": "participants/CARNAGE.png?v=1694789076640",
      "externalId": "NB080230625",
      "homeParticipantName": "THA KID",
      "awayTeamAbbreviation": "PHX",
      "groupName": null,
      "leagueId": null,
      "fixtureExternalId": "NB080230625",
      "homeTeamExternalId": null,
      "tournamentId": 1,
      "fixtureId": 241907,
      "awayParticipantName": "CARNAGE",
      "awayParticipantExternalId": "1239",
      "homeTeamAbbreviation": "MEM",
      "startDate": "2025-06-23T12:59:00Z",
      "leagueLogo": null,
      "awayTeamId": 24,
      "awayTeamLogo": "teams/Phoenix_Suns.svg",
      "streamName": "Ebasketball 2",
      "homeParticipantLogo": "participants/THA KID.png"
    }
  },
  {
    "id": 241807,
    "homePlayer": {
      "id": 456,
      "name": "PRIMAL"
    },
    "awayPlayer": {
      "id": 509,
      "name": "SPECTER"
    },
    "homeTeam": {
      "id": 2,
      "name": "Brooklyn Nets"
    },
    "awayTeam": {
      "id": 16,
      "name": "Miami Heat"
    },
    "fixtureStart": "2025-06-23T13:07:00Z",
    "raw_data": {
      "sport": "NBA",
      "avaStreamId": "sis-nba-3",
      "leagueName": null,
      "awayParticipantId": 509,
      "tournamentName": "Ebasketball H2H GG League",
      "homeParticipantExternalId": "4643",
      "fixtureStart": "2025-06-23T13:07:00Z",
      "homeTeamId": 2,
      "groupId": null,
      "awayTeamName": "Miami Heat",
      "homeParticipantId": 456,
      "homeTeamLogo": "teams/Brooklyn_Nets.svg",
      "awayTeamExternalId": null,
      "roundName": "Ebasketball H2H GG League round 1",
      "roundId": 1,
      "homeTeamName": "Brooklyn Nets",
      "awayParticipantLogo": "participants/SPECTER.png?v=1740572872596",
      "externalId": "NB081230625",
      "homeParticipantName": "PRIMAL",
      "awayTeamAbbreviation": "MIA",
      "groupName": null,
      "leagueId": null,
      "fixtureExternalId": "NB081230625",
      "homeTeamExternalId": null,
      "tournamentId": 1,
      "fixtureId": 241807,
      "awayParticipantName": "SPECTER",
      "awayParticipantExternalId": "4817",
      "homeTeamAbbreviation": "BKN",
      "startDate": "2025-06-23T13:07:00Z",
      "leagueLogo": null,
      "awayTeamId": 16,
      "awayTeamLogo": "teams/MH.png",
      "streamName": "Ebasketball 3",
      "homeParticipantLogo": "participants/PRIMAL.png?v=1722868829330"
    }
  },
  {
    "id": 241855,
    "homePlayer": {
      "id": 2249,
      "name": "DOC"
    },
    "awayPlayer": {
      "id": 91,
      "name": "DOUBLEFOUR"
    },
    "homeTeam": {
      "id": 7,
      "name": "Dallas Mavericks"
    },
    "awayTeam": {
      "id": 4,
      "name": "Charlotte Hornets"
    },
    "fixtureStart": "2025-06-23T13:15:00Z",
    "raw_data": {
      "sport": "NBA",
      "avaStreamId": "sis-nba-4",
      "leagueName": null,
      "awayParticipantId": 91,
      "tournamentName": "Ebasketball H2H GG League",
      "homeParticipantExternalId": "4235",
      "fixtureStart": "2025-06-23T13:15:00Z",
      "homeTeamId": 7,
      "groupId": null,
      "awayTeamName": "Charlotte Hornets",
      "homeParticipantId": 2249,
      "homeTeamLogo": "teams/Dallas_Mavericks.svg",
      "awayTeamExternalId": null,
      "roundName": "Ebasketball H2H GG League round 1",
      "roundId": 1,
      "homeTeamName": "Dallas Mavericks",
      "awayParticipantLogo": "participants/DOUBLEFOUR.png",
      "externalId": "NB082230625",
      "homeParticipantName": "DOC",
      "awayTeamAbbreviation": "CHA",
      "groupName": null,
      "leagueId": null,
      "fixtureExternalId": "NB082230625",
      "homeTeamExternalId": null,
      "tournamentId": 1,
      "fixtureId": 241855,
      "awayParticipantName": "DOUBLEFOUR",
      "awayParticipantExternalId": "1066",
      "homeTeamAbbreviation": "DAL",
      "startDate": "2025-06-23T13:15:00Z",
      "leagueLogo": null,
      "awayTeamId": 4,
      "awayTeamLogo": "teams/CH.png",
      "streamName": "Ebasketball 4",
      "homeParticipantLogo": "participants/default-player-profile.png"
    }
  },
  {
    "id": 241878,
    "homePlayer": {
      "id": 27,
      "name": "DIMES"
    },
    "awayPlayer": {
      "id": 957,
      "name": "EXO"
    },
    "homeTeam": {
      "id": 7,
      "name": "Dallas Mavericks"
    },
    "awayTeam": {
      "id": 22,
      "name": "Orlando Magic"
    },
    "fixtureStart": "2025-06-23T13:23:00Z",
    "raw_data": {
      "sport": "NBA",
      "avaStreamId": "sis-nba-1",
      "leagueName": null,
      "awayParticipantId": 957,
      "tournamentName": "Ebasketball H2H GG League",
      "homeParticipantExternalId": "1214",
      "fixtureStart": "2025-06-23T13:23:00Z",
      "homeTeamId": 7,
      "groupId": null,
      "awayTeamName": "Orlando Magic",
      "homeParticipantId": 27,
      "homeTeamLogo": "teams/Dallas_Mavericks.svg",
      "awayTeamExternalId": null,
      "roundName": "Ebasketball H2H GG League round 1",
      "roundId": 1,
      "homeTeamName": "Dallas Mavericks",
      "awayParticipantLogo": "participants/EXO.png?v=1738341274121",
      "externalId": "NB083230625",
      "homeParticipantName": "DIMES",
      "awayTeamAbbreviation": "ORL",
      "groupName": null,
      "leagueId": null,
      "fixtureExternalId": "NB083230625",
      "homeTeamExternalId": null,
      "tournamentId": 1,
      "fixtureId": 241878,
      "awayParticipantName": "EXO",
      "awayParticipantExternalId": "4286",
      "homeTeamAbbreviation": "DAL",
      "startDate": "2025-06-23T13:23:00Z",
      "leagueLogo": null,
      "awayTeamId": 22,
      "awayTeamLogo": "teams/OM.png",
      "streamName": "Ebasketball 1",
      "homeParticipantLogo": "participants/DIMES.png"
    }
  },
  {
    "id": 241912,
    "homePlayer": {
      "id": 14,
      "name": "CARNAGE"
    },
    "awayPlayer": {
      "id": 105,
      "name": "KJMR"
    },
    "homeTeam": {
      "id": 24,
      "name": "Phoenix Suns"
    },
    "awayTeam": {
      "id": 17,
      "name": "Milwaukee Bucks"
    },
    "fixtureStart": "2025-06-23T13:31:00Z",
    "raw_data": {
      "sport": "NBA",
      "avaStreamId": "sis-nba-2",
      "leagueName": null,
      "awayParticipantId": 105,
      "tournamentName": "Ebasketball H2H GG League",
      "homeParticipantExternalId": "1239",
      "fixtureStart": "2025-06-23T13:31:00Z",
      "homeTeamId": 24,
      "groupId": null,
      "awayTeamName": "Milwaukee Bucks",
      "homeParticipantId": 14,
      "homeTeamLogo": "teams/Phoenix_Suns.svg",
      "awayTeamExternalId": null,
      "roundName": "Ebasketball H2H GG League round 1",
      "roundId": 1,
      "homeTeamName": "Phoenix Suns",
      "awayParticipantLogo": "participants/KJMR.png",
      "externalId": "NB084230625",
      "homeParticipantName": "CARNAGE",
      "awayTeamAbbreviation": "MIL",
      "groupName": null,
      "leagueId": null,
      "fixtureExternalId": "NB084230625",
      "homeTeamExternalId": null,
      "tournamentId": 1,
      "fixtureId": 241912,
      "awayParticipantName": "KJMR",
      "awayParticipantExternalId": "1078",
      "homeTeamAbbreviation": "PHX",
      "startDate": "2025-06-23T13:31:00Z",
      "leagueLogo": null,
      "awayTeamId": 17,
      "awayTeamLogo": "teams/Milwaukee_Bucks.svg",
      "streamName": "Ebasketball 2",
      "homeParticipantLogo": "participants/CARNAGE.png?v=1694789076640"
    }
  },
  {
    "id": 241811,
    "homePlayer": {
      "id": 509,
      "name": "SPECTER"
    },
    "awayPlayer": {
      "id": 160,
      "name": "JUGGERNAUT"
    },
    "homeTeam": {
      "id": 17,
      "name": "Milwaukee Bucks"
    },
    "awayTeam": {
      "id": 6,
      "name": "Cleveland Cavaliers"
    },
    "fixtureStart": "2025-06-23T13:39:00Z",
    "raw_data": {
      "sport": "NBA",
      "avaStreamId": "sis-nba-3",
      "leagueName": null,
      "awayParticipantId": 160,
      "tournamentName": "Ebasketball H2H GG League",
      "homeParticipantExternalId": "4817",
      "fixtureStart": "2025-06-23T13:39:00Z",
      "homeTeamId": 17,
      "groupId": null,
      "awayTeamName": "Cleveland Cavaliers",
      "homeParticipantId": 509,
      "homeTeamLogo": "teams/Milwaukee_Bucks.svg",
      "awayTeamExternalId": null,
      "roundName": "Ebasketball H2H GG League round 1",
      "roundId": 1,
      "homeTeamName": "Milwaukee Bucks",
      "awayParticipantLogo": "participants/JUGGERNAUT.png?v=1714142097517",
      "externalId": "NB085230625",
      "homeParticipantName": "SPECTER",
      "awayTeamAbbreviation": "CLE",
      "groupName": null,
      "leagueId": null,
      "fixtureExternalId": "NB085230625",
      "homeTeamExternalId": null,
      "tournamentId": 1,
      "fixtureId": 241811,
      "awayParticipantName": "JUGGERNAUT",
      "awayParticipantExternalId": "1269",
      "homeTeamAbbreviation": "MIL",
      "startDate": "2025-06-23T13:39:00Z",
      "leagueLogo": null,
      "awayTeamId": 6,
      "awayTeamLogo": "teams/Cleveland_Cavaliers.svg",
      "streamName": "Ebasketball 3",
      "homeParticipantLogo": "participants/SPECTER.png?v=1740572872596"
    }
  },
  {
    "id": 241846,
    "homePlayer": {
      "id": 91,
      "name": "DOUBLEFOUR"
    },
    "awayPlayer": {
      "id": 1433,
      "name": "HERO"
    },
    "homeTeam": {
      "id": 14,
      "name": "Los Angeles Lakers"
    },
    "awayTeam": {
      "id": 3,
      "name": "Boston Celtics"
    },
    "fixtureStart": "2025-06-23T13:47:00Z",
    "raw_data": {
      "sport": "NBA",
      "avaStreamId": "sis-nba-4",
      "leagueName": null,
      "awayParticipantId": 1433,
      "tournamentName": "Ebasketball H2H GG League",
      "homeParticipantExternalId": "1066",
      "fixtureStart": "2025-06-23T13:47:00Z",
      "homeTeamId": 14,
      "groupId": null,
      "awayTeamName": "Boston Celtics",
      "homeParticipantId": 91,
      "homeTeamLogo": "teams/Los_Angeles_Lakers.svg",
      "awayTeamExternalId": null,
      "roundName": "Ebasketball H2H GG League round 1",
      "roundId": 1,
      "homeTeamName": "Los Angeles Lakers",
      "awayParticipantLogo": "participants/HERO_1.png?v=1740571931509",
      "externalId": "NB086230625",
      "homeParticipantName": "DOUBLEFOUR",
      "awayTeamAbbreviation": "BOS",
      "groupName": null,
      "leagueId": null,
      "fixtureExternalId": "NB086230625",
      "homeTeamExternalId": null,
      "tournamentId": 1,
      "fixtureId": 241846,
      "awayParticipantName": "HERO",
      "awayParticipantExternalId": "4401",
      "homeTeamAbbreviation": "LAL",
      "startDate": "2025-06-23T13:47:00Z",
      "leagueLogo": null,
      "awayTeamId": 3,
      "awayTeamLogo": "teams/Boston_Celtics.svg",
      "streamName": "Ebasketball 4",
      "homeParticipantLogo": "participants/DOUBLEFOUR.png"
    }
  },
  {
    "id": 241889,
    "homePlayer": {
      "id": 159,
      "name": "HOLLOW"
    },
    "awayPlayer": {
      "id": 751,
      "name": "JACKAL"
    },
    "homeTeam": {
      "id": 8,
      "name": "Denver Nuggets"
    },
    "awayTeam": {
      "id": 4,
      "name": "Charlotte Hornets"
    },
    "fixtureStart": "2025-06-23T13:55:00Z",
    "raw_data": {
      "sport": "NBA",
      "avaStreamId": "sis-nba-1",
      "leagueName": null,
      "awayParticipantId": 751,
      "tournamentName": "Ebasketball H2H GG League",
      "homeParticipantExternalId": "1268",
      "fixtureStart": "2025-06-23T13:55:00Z",
      "homeTeamId": 8,
      "groupId": null,
      "awayTeamName": "Charlotte Hornets",
      "homeParticipantId": 159,
      "homeTeamLogo": "teams/DN.png",
      "awayTeamExternalId": null,
      "roundName": "Ebasketball H2H GG League round 1",
      "roundId": 1,
      "homeTeamName": "Denver Nuggets",
      "awayParticipantLogo": "participants/JACKAL.png?v=1738342862838",
      "externalId": "NB087230625",
      "homeParticipantName": "HOLLOW",
      "awayTeamAbbreviation": "CHA",
      "groupName": null,
      "leagueId": null,
      "fixtureExternalId": "NB087230625",
      "homeTeamExternalId": null,
      "tournamentId": 1,
      "fixtureId": 241889,
      "awayParticipantName": "JACKAL",
      "awayParticipantExternalId": "4445",
      "homeTeamAbbreviation": "DEN",
      "startDate": "2025-06-23T13:55:00Z",
      "leagueLogo": null,
      "awayTeamId": 4,
      "awayTeamLogo": "teams/CH.png",
      "streamName": "Ebasketball 1",
      "homeParticipantLogo": "participants/HOLLOW.png?v=1714140827775"
    }
  },
  {
    "id": 241902,
    "homePlayer": {
      "id": 66,
      "name": "THA KID"
    },
    "awayPlayer": {
      "id": 102,
      "name": "SKYFOX"
    },
    "homeTeam": {
      "id": 15,
      "name": "Memphis Grizzlies"
    },
    "awayTeam": {
      "id": 6,
      "name": "Cleveland Cavaliers"
    },
    "fixtureStart": "2025-06-23T14:03:00Z",
    "raw_data": {
      "sport": "NBA",
      "avaStreamId": "sis-nba-2",
      "leagueName": null,
      "awayParticipantId": 102,
      "tournamentName": "Ebasketball H2H GG League",
      "homeParticipantExternalId": "1023",
      "fixtureStart": "2025-06-23T14:03:00Z",
      "homeTeamId": 15,
      "groupId": null,
      "awayTeamName": "Cleveland Cavaliers",
      "homeParticipantId": 66,
      "homeTeamLogo": "teams/Memphis_Grizzlies.svg",
      "awayTeamExternalId": null,
      "roundName": "Ebasketball H2H GG League round 1",
      "roundId": 1,
      "homeTeamName": "Memphis Grizzlies",
      "awayParticipantLogo": "participants/SKYFOX.png",
      "externalId": "NB088230625",
      "homeParticipantName": "THA KID",
      "awayTeamAbbreviation": "CLE",
      "groupName": null,
      "leagueId": null,
      "fixtureExternalId": "NB088230625",
      "homeTeamExternalId": null,
      "tournamentId": 1,
      "fixtureId": 241902,
      "awayParticipantName": "SKYFOX",
      "awayParticipantExternalId": "1211",
      "homeTeamAbbreviation": "MEM",
      "startDate": "2025-06-23T14:03:00Z",
      "leagueLogo": null,
      "awayTeamId": 6,
      "awayTeamLogo": "teams/Cleveland_Cavaliers.svg",
      "streamName": "Ebasketball 2",
      "homeParticipantLogo": "participants/THA KID.png"
    }
  },
  {
    "id": 241826,
    "homePlayer": {
      "id": 456,
      "name": "PRIMAL"
    },
    "awayPlayer": {
      "id": 1169,
      "name": "GODFATHER"
    },
    "homeTeam": {
      "id": 2,
      "name": "Brooklyn Nets"
    },
    "awayTeam": {
      "id": 5,
      "name": "Chicago Bulls"
    },
    "fixtureStart": "2025-06-23T14:11:00Z",
    "raw_data": {
      "sport": "NBA",
      "avaStreamId": "sis-nba-3",
      "leagueName": null,
      "awayParticipantId": 1169,
      "tournamentName": "Ebasketball H2H GG League",
      "homeParticipantExternalId": "4643",
      "fixtureStart": "2025-06-23T14:11:00Z",
      "homeTeamId": 2,
      "groupId": null,
      "awayTeamName": "Chicago Bulls",
      "homeParticipantId": 456,
      "homeTeamLogo": "teams/Brooklyn_Nets.svg",
      "awayTeamExternalId": null,
      "roundName": "Ebasketball H2H GG League round 1",
      "roundId": 1,
      "homeTeamName": "Brooklyn Nets",
      "awayParticipantLogo": "participants/GODFATHER.png?v=1738342374988",
      "externalId": "NB089230625",
      "homeParticipantName": "PRIMAL",
      "awayTeamAbbreviation": "CHI",
      "groupName": null,
      "leagueId": null,
      "fixtureExternalId": "NB089230625",
      "homeTeamExternalId": null,
      "tournamentId": 1,
      "fixtureId": 241826,
      "awayParticipantName": "GODFATHER",
      "awayParticipantExternalId": "4348",
      "homeTeamAbbreviation": "BKN",
      "startDate": "2025-06-23T14:11:00Z",
      "leagueLogo": null,
      "awayTeamId": 5,
      "awayTeamLogo": "teams/CB.png",
      "streamName": "Ebasketball 3",
      "homeParticipantLogo": "participants/PRIMAL.png?v=1722868829330"
    }
  },
  {
    "id": 241848,
    "homePlayer": {
      "id": 2249,
      "name": "DOC"
    },
    "awayPlayer": {
      "id": 1219,
      "name": "ABYSS"
    },
    "homeTeam": {
      "id": 7,
      "name": "Dallas Mavericks"
    },
    "awayTeam": {
      "id": 22,
      "name": "Orlando Magic"
    },
    "fixtureStart": "2025-06-23T14:19:00Z",
    "raw_data": {
      "sport": "NBA",
      "avaStreamId": "sis-nba-4",
      "leagueName": null,
      "awayParticipantId": 1219,
      "tournamentName": "Ebasketball H2H GG League",
      "homeParticipantExternalId": "4235",
      "fixtureStart": "2025-06-23T14:19:00Z",
      "homeTeamId": 7,
      "groupId": null,
      "awayTeamName": "Orlando Magic",
      "homeParticipantId": 2249,
      "homeTeamLogo": "teams/Dallas_Mavericks.svg",
      "awayTeamExternalId": null,
      "roundName": "Ebasketball H2H GG League round 1",
      "roundId": 1,
      "homeTeamName": "Dallas Mavericks",
      "awayParticipantLogo": "participants/ABYSS.png?v=1738339090802",
      "externalId": "NB090230625",
      "homeParticipantName": "DOC",
      "awayTeamAbbreviation": "ORL",
      "groupName": null,
      "leagueId": null,
      "fixtureExternalId": "NB090230625",
      "homeTeamExternalId": null,
      "tournamentId": 1,
      "fixtureId": 241848,
      "awayParticipantName": "ABYSS",
      "awayParticipantExternalId": "4001",
      "homeTeamAbbreviation": "DAL",
      "startDate": "2025-06-23T14:19:00Z",
      "leagueLogo": null,
      "awayTeamId": 22,
      "awayTeamLogo": "teams/OM.png",
      "streamName": "Ebasketball 4",
      "homeParticipantLogo": "participants/default-player-profile.png"
    }
  }
]